{
    "posts": [
      {
        "id": "1",
        "title": "Theca ducimus calcar vinco trepide omnis ex accedo.",
        "views": 100
      },
      {
        "id": "2",
        "title": "Comitatus ducimus comedo tabula supplanto rem defungo coruscus.",
        "views": 133
      },
      {
        "id": "3",
        "title": "a title",
        "views": 100
      },
      {
        "id": "4",
        "title": "Venustas aeternus alius trucido aestivus vilitas amoveo nemo quo.",
        "views": 59
      },
      {
        "id": "5",
        "title": "Tergiversatio vero aliquam arcus alias cavus voluptates arbustum decipio textor.",
        "views": 85
      },
      {
        "id": "6",
        "title": "Coerceo tactus vos timor voluptates corroboro.",
        "views": 64
      },
      {
        "id": "7",
        "title": "Desolo velit speculum thalassinus adfectus ventosus summopere toties dignissimos.",
        "views": 67
      },
      {
        "id": "8",
        "title": "Advoco fuga subvenio.",
        "views": 24
      },
      {
        "id": "9",
        "title": "Commodo fuga conitor subiungo voluntarius virga saepe tergo audax calcar.",
        "views": 55
      },
      {
        "id": "10",
        "title": "Ter civis tyrannus.",
        "views": 31
      },
      {
        "id": "11",
        "title": "Supra crastinus claudeo pecus trans qui.",
        "views": 100
      },
      {
        "id": "12",
        "title": "Capitulus theca arbor vinco ver.",
        "views": 26
      },
      {
        "id": "13",
        "title": "Audacia subnecto deduco aspicio ars modi.",
        "views": 16
      }
    ],
    "comments": [
      {
        "id": "1",
        "text": "a comment about post 1",
        "postId": "1"
      },
      {
        "id": "2",
        "text": "another comment about post 1",
        "postId": "1"
      }
    ],
    "profile": {
      "name": "typicode"
    }
  }
  